Metadata-Version: 2.1
Name: sqlalchemy-crud-base
Version: 0.1.3
Summary: A SQLAlchemy-based CRUD package
Home-page: https://github.com/Seuleeee/sqlalchemy-crud-base
Author: HanSeul Jo
Author-email: bryantjo1224@gmail.com
License: UNKNOWN
Platform: UNKNOWN
Classifier: Programming Language :: Python :: 3
Classifier: Operating System :: OS Independent
Requires-Python: >=3.8
License-File: LICENSE
